understatscraper/__init__.py
understatscraper-0.0.2.dist-info/LICENSE.txt
understatscraper-0.0.2.dist-info/METADATA
understatscraper-0.0.2.dist-info/WHEEL
understatscraper-0.0.2.dist-info/top_level.txt
understatscraper-0.0.2.dist-info/RECORD
