Metadata-Version: 2.1
Name: understatscraper
Version: 0.0.2
Summary: A Python package to scrape shots data from understat.com for either a single game or a whole season.
Home-page: https://github.com/Shivank12batra/understatscraper
Author: Shivank Batra
Author-email: Shivank56batra@gmail.com
License: MIT License
Platform: UNKNOWN
Classifier: Development Status :: 3 - Alpha
Classifier: Intended Audience :: Developers
Classifier: License :: OSI Approved :: MIT License
Classifier: Programming Language :: Python :: 3
Classifier: Programming Language :: Python :: 3.8
Requires-Dist: numpy
Requires-Dist: pandas
Requires-Dist: requests
Requires-Dist: bs4
Requires-Dist: lxml
